igmov/__init__.py
igmov/analyzer.py
igmov/dl.py
igmov/draw.py
igmov/template/__init__.py
igmov/template/ig.py
igmov/template/igtv.py
igmov/template/youtube.py
igmov-0.0.5.dist-info/LICENSE
igmov-0.0.5.dist-info/METADATA
igmov-0.0.5.dist-info/WHEEL
igmov-0.0.5.dist-info/top_level.txt
igmov-0.0.5.dist-info/RECORD
