Metadata-Version: 2.1
Name: igmov
Version: 0.0.5
Summary: Video generator using Ngupuk templates.
Home-page: https://github.com/ngupuk/igmov
Author: Ngupuk
Author-email: wafax.4@gmail.com
License: MIT
Keywords: Python,video,editor
Platform: any
Classifier: Programming Language :: Python
Requires-Python: >= 3.5.*
Requires-Dist: urllib3
Requires-Dist: moviepy
Requires-Dist: numpy
Requires-Dist: Pillow
